setup.py
latex2word/__init__.py
latex2word/convert.py
latex2word/handler.py
latex2word-1.1.dist-info/LICENSE
latex2word-1.1.dist-info/METADATA
latex2word-1.1.dist-info/WHEEL
latex2word-1.1.dist-info/top_level.txt
latex2word-1.1.dist-info/RECORD
