Metadata-Version: 2.1
Name: latex2word
Version: 1.1
Summary: A pure python library implemented by python3 for writing Latex formulas to word.
Author: Gu-f
Project-URL: Homepage, https://github.com/Gu-f/LatexToWord
Project-URL: Bug Tracker, https://github.com/Gu-f/LatexToWord/issues
Classifier: Programming Language :: Python :: 3
Classifier: License :: OSI Approved :: MIT License
Classifier: Operating System :: OS Independent
Requires-Python: >=3.7
License-File: LICENSE
Requires-Dist: mathml2omml ~=0.0.2
Requires-Dist: latex2mathml ~=3.77.0
Requires-Dist: lxml ~=5.3.0
